TextgroceryZhongwenApi/README.md
TextgroceryZhongwenApi/__init__.py
TextgroceryZhongwenApi/__main__.py
TextgroceryZhongwenApi/file.epub
TextgroceryZhongwenApi/index.html
TextgroceryZhongwenApi/css/__init__.py
TextgroceryZhongwenApi/css/annotations.css
TextgroceryZhongwenApi/css/main.css
TextgroceryZhongwenApi/css/normalize.css
TextgroceryZhongwenApi/css/popup.css
TextgroceryZhongwenApi/font/__init__.py
TextgroceryZhongwenApi/font/fontello.eot
TextgroceryZhongwenApi/font/fontello.svg
TextgroceryZhongwenApi/font/fontello.ttf
TextgroceryZhongwenApi/font/fontello.woff
TextgroceryZhongwenApi/img/__init__.py
TextgroceryZhongwenApi/img/annotator-glyph-sprite.png
TextgroceryZhongwenApi/img/annotator-icon-sprite.png
TextgroceryZhongwenApi/img/apple-touch-icon.png
TextgroceryZhongwenApi/img/cancelfullscreen.png
TextgroceryZhongwenApi/img/close.png
TextgroceryZhongwenApi/img/fullscreen.png
TextgroceryZhongwenApi/img/loader.gif
TextgroceryZhongwenApi/img/menu-icon.png
TextgroceryZhongwenApi/img/save.png
TextgroceryZhongwenApi/img/saved.png
TextgroceryZhongwenApi/img/settings-s.png
TextgroceryZhongwenApi/img/settings.png
TextgroceryZhongwenApi/img/star.png
TextgroceryZhongwenApi/js/__init__.py
TextgroceryZhongwenApi/js/epub.js
TextgroceryZhongwenApi/js/epub.min.js
TextgroceryZhongwenApi/js/epub.min.map
TextgroceryZhongwenApi/js/hooks.min.js
TextgroceryZhongwenApi/js/hooks.min.map
TextgroceryZhongwenApi/js/reader.js
TextgroceryZhongwenApi/js/reader.js.map
TextgroceryZhongwenApi/js/reader.min.js
TextgroceryZhongwenApi/js/reader.min.map
TextgroceryZhongwenApi/js/hooks/__init__.py
TextgroceryZhongwenApi/js/hooks/extensions/__init__.py
TextgroceryZhongwenApi/js/hooks/extensions/highlight.js
TextgroceryZhongwenApi/js/libs/__init__.py
TextgroceryZhongwenApi/js/libs/jquery.min.js
TextgroceryZhongwenApi/js/libs/localforage.min.js
TextgroceryZhongwenApi/js/libs/screenfull.js
TextgroceryZhongwenApi/js/libs/screenfull.min.js
TextgroceryZhongwenApi/js/libs/zip.min.js
textgrocery_zhongwen_api-2024.3.2.0.dist-info/METADATA
textgrocery_zhongwen_api-2024.3.2.0.dist-info/WHEEL
textgrocery_zhongwen_api-2024.3.2.0.dist-info/entry_points.txt
textgrocery_zhongwen_api-2024.3.2.0.dist-info/top_level.txt
textgrocery_zhongwen_api-2024.3.2.0.dist-info/RECORD
